pyyamlsettings/__init__.py
pyyamlsettings/descriptors.py
pyyamlsettings/errors.py
pyyamlsettings/settings.py
tests/__init__.py
tests/test_descriptors.py
tests/test_errors.py
tests/test_settings.py
pyyamlsettings-0.0.4.dist-info/LICENSE
pyyamlsettings-0.0.4.dist-info/METADATA
pyyamlsettings-0.0.4.dist-info/WHEEL
pyyamlsettings-0.0.4.dist-info/top_level.txt
pyyamlsettings-0.0.4.dist-info/RECORD
