Metadata-Version: 2.1
Name: pyyamlsettings
Version: 0.0.4
Summary: A Flyweight pattern for loading yaml files
Home-page: https://github.com/simongarisch/pyyamlsettings
Author: Simon Garisch
Author-email: gatman946@gmail.com
License: UNKNOWN
Platform: UNKNOWN
Requires-Dist: PyYAML (>=5.1)
